gsflow/__init__.py
gsflow/control.py
gsflow/gsflow.py
gsflow/param_base.py
gsflow/record_base.py
gsflow/builder/__init__.py
gsflow/builder/builder_defaults.py
gsflow/builder/builder_utils.py
gsflow/builder/controlfile_builder.py
gsflow/builder/defaults.json
gsflow/builder/fishnet.py
gsflow/builder/flow_accumulation.py
gsflow/builder/make_json_defaults.py
gsflow/builder/modflow_builder.py
gsflow/builder/prms_builder.py
gsflow/crt/__init__.py
gsflow/crt/crt.py
gsflow/modflow/__init__.py
gsflow/modflow/mf.py
gsflow/modflow/mfag.py
gsflow/modflow/mfawu.py
gsflow/modsim/__init__.py
gsflow/modsim/epsg_to_wkt.dat
gsflow/modsim/modsim.py
gsflow/output/__init__.py
gsflow/output/discretization.py
gsflow/output/prms_output.py
gsflow/output/prms_plot.py
gsflow/prms/__init__.py
gsflow/prms/gsflow_prms.control.par_name
gsflow/prms/gsflow_prms.control.var_name
gsflow/prms/prms_data.py
gsflow/prms/prms_day.py
gsflow/prms/prms_dynamic_params.py
gsflow/prms/prms_help.py
gsflow/prms/prms_model.py
gsflow/prms/prms_parameter.py
gsflow/utils/__init__.py
gsflow/utils/constants.py
gsflow/utils/gsflow_io.py
gsflow/utils/mfreadnam.py
gsflow/utils/netcdf.py
gsflow/utils/numba.py
gsflow/utils/rasters.py
gsflow/utils/sfr_renumber.py
gsflow/utils/vtk.py
pygsflow-1.1.0.dist-info/LICENSE.md
pygsflow-1.1.0.dist-info/METADATA
pygsflow-1.1.0.dist-info/WHEEL
pygsflow-1.1.0.dist-info/top_level.txt
pygsflow-1.1.0.dist-info/RECORD
