Metadata-Version: 2.1
Name: pygsflow
Version: 1.1.0
Summary: pyGSFLOW is a python package to create, run, and post-process GSFLOW-based models
Home-page: https://github.com/pygsflow/pygsflow
Author: Ayman Alzraiee, Joshua Larsen, Rich Niswonger, Donald Martin
Author-email: aalzraiee@usgs.gov, jlarsen@usgs.gov, rniswon@usgs.gov, domartin@usgs.gov
License: MIT license
Keywords: gsflow
Classifier: Development Status :: 5 - Production/Stable
Classifier: Intended Audience :: Developers
Classifier: License :: OSI Approved :: MIT License
Classifier: Natural Language :: English
Classifier: Programming Language :: Python :: 3 :: Only
Classifier: Programming Language :: Python :: 3.5
Classifier: Programming Language :: Python :: 3.6
Classifier: Programming Language :: Python :: 3.7
Classifier: Programming Language :: Python :: 3.8
Classifier: Topic :: Scientific/Engineering :: Hydrology
Classifier: Operating System :: OS Independent
Requires-Python: >=3.6
License-File: LICENSE.md
Requires-Dist: pandas
Requires-Dist: numpy
Requires-Dist: flopy (>=3.3.4)
Requires-Dist: pyshp
Requires-Dist: pycrs
Requires-Dist: matplotlib
